ael/__init__.py
ael/client.py
ael/context.py
ael/decorators.py
ael/integrations/__init__.py
ael/integrations/autogen.py
ael/integrations/crewai.py
ael/integrations/google_adk.py
ael/integrations/langchain.py
ael/integrations/openai_assistants.py
ael_sdk-0.3.0.dist-info/licenses/LICENSE
ael_sdk-0.3.0.dist-info/METADATA
ael_sdk-0.3.0.dist-info/WHEEL
ael_sdk-0.3.0.dist-info/top_level.txt
ael_sdk-0.3.0.dist-info/RECORD
