Metadata-Version: 2.4
Name: ael-sdk
Version: 0.3.0
Summary: Python SDK for Agent Execution Ledger - Audit trail for AI agents
Home-page: https://github.com/vinayb21-work/Agent-Execution-Ledger
Author: Vinay Badhan
Author-email: vinay.badhan21.work@gmail.com
Project-URL: Bug Tracker, https://github.com/vinayb21-work/Agent-Execution-Ledger/issues
Project-URL: Documentation, https://github.com/vinayb21-work/Agent-Execution-Ledger#readme
Keywords: ai agents audit logging llm observability
Classifier: Development Status :: 3 - Alpha
Classifier: Intended Audience :: Developers
Classifier: License :: OSI Approved :: MIT License
Classifier: Operating System :: OS Independent
Classifier: Programming Language :: Python :: 3
Classifier: Programming Language :: Python :: 3.9
Classifier: Programming Language :: Python :: 3.10
Classifier: Programming Language :: Python :: 3.11
Classifier: Programming Language :: Python :: 3.12
Classifier: Topic :: Software Development :: Libraries :: Python Modules
Classifier: Topic :: System :: Logging
Requires-Python: >=3.9
License-File: LICENSE
Requires-Dist: httpx>=0.26.0
Requires-Dist: pydantic>=2.5.0
Provides-Extra: google-adk
Requires-Dist: google-adk>=1.0.0; extra == "google-adk"
Provides-Extra: langchain
Requires-Dist: langchain-core>=0.1.0; extra == "langchain"
Provides-Extra: crewai
Requires-Dist: crewai>=0.1.0; extra == "crewai"
Provides-Extra: openai
Requires-Dist: openai>=1.0.0; extra == "openai"
Provides-Extra: autogen
Requires-Dist: pyautogen>=0.2.0; extra == "autogen"
Provides-Extra: all
Requires-Dist: google-adk>=1.0.0; extra == "all"
Requires-Dist: langchain-core>=0.1.0; extra == "all"
Requires-Dist: crewai>=0.1.0; extra == "all"
Requires-Dist: openai>=1.0.0; extra == "all"
Requires-Dist: pyautogen>=0.2.0; extra == "all"
Dynamic: author
Dynamic: author-email
Dynamic: classifier
Dynamic: description
Dynamic: description-content-type
Dynamic: home-page
Dynamic: keywords
Dynamic: license-file
Dynamic: project-url
Dynamic: provides-extra
Dynamic: requires-dist
Dynamic: requires-python
Dynamic: summary
